Metadata-Version: 2.1
Name: midtools
Version: 1.1.1
Summary: Command line scripts and Python classes for detecting multiple infections from NGS reads.
Home-page: https://github.com/acorg/midtools
Download-URL: https://github.com/acorg/midtools
Author: Terry Jones
Author-email: tcj25@cam.ac.uk
License: MIT
Keywords: genetic sequences
Classifier: Programming Language :: Python :: 2.7
Classifier: Programming Language :: Python :: 3.5
Classifier: Programming Language :: Python :: 3.6
Classifier: Development Status :: 4 - Beta
Classifier: Intended Audience :: Developers
Classifier: License :: OSI Approved :: MIT License
Classifier: Operating System :: OS Independent
Classifier: Topic :: Software Development :: Libraries :: Python Modules
Requires-Dist: dark-matter>=4.0.6
Requires-Dist: plotly>=2.7.0
Requires-Dist: flake8>=3.5.0
